cemir_print/__init__.py
cemir_print/ccprint.py
cemir_print-202231005.2.dist-info/LICENSE
cemir_print-202231005.2.dist-info/METADATA
cemir_print-202231005.2.dist-info/WHEEL
cemir_print-202231005.2.dist-info/top_level.txt
cemir_print-202231005.2.dist-info/RECORD
