Metadata-Version: 2.1
Name: cemir-print
Version: 202231005.2
Summary: A colorful printing library for Python
Home-page: https://github.com/muslu/cemir_print
Author: muslu yüksektepe
Author-email: musluyuksektepe@gmail.com
License: UNKNOWN
Platform: UNKNOWN
Classifier: License :: OSI Approved :: MIT License
Classifier: Programming Language :: Python :: 3
Classifier: Programming Language :: Python :: 3.6
Classifier: Programming Language :: Python :: 3.7
Classifier: Programming Language :: Python :: 3.8
License-File: LICENSE
